sample/__init__.py
src/__init__.py
src/js.py
src/main.py
chart_server-0.0.1.dist-info/METADATA
chart_server-0.0.1.dist-info/WHEEL
chart_server-0.0.1.dist-info/top_level.txt
chart_server-0.0.1.dist-info/RECORD
