Metadata-Version: 2.1
Name: chart-server
Version: 0.0.1
Summary: lightweight-chart custom python server
Home-page: https://github.com/vegaxholdings/chart-server
Author: Won JeongHoo
Author-email: clomia.sig@gmail.com
Classifier: Programming Language :: Python :: 3
Classifier: License :: OSI Approved :: MIT License
Classifier: Operating System :: OS Independent
Requires-Python: >=3.10
Requires-Dist: fastapi ==0.111.1
Requires-Dist: lightweight-charts ==2.0.1
